{
  "upcomingSessions": [
    {
      "id": "group_001",
      "title": "Data Structures Study Group",
      "topic": "Trees and Graphs",
      "host": {
        "id": "user_124",
        "username": "alice",
        "avatarUrl": "https://api.dicebear.com/7.x/avataaars/svg?seed=Alice"
      },
      "scheduledAt": "2023-06-18T16:00:00Z",
      "duration": 90,
      "participants": 4,
      "maxParticipants": 8,
      "isJoined": false
    },
    {
      "id": "group_fc1f3b2d",
      "title": "Dl",
      "topic": "adfafadf",
      "description": "",
      "host": {
        "id": "user_124",
        "username": "alice",
        "avatarUrl": "https://api.dicebear.com/7.x/avataaars/svg?seed=Alice"
      },
      "scheduledAt": "2025-10-18T16:04:07.054Z",
      "duration": 90,
      "maxParticipants": 8,
      "participants": [
        {
          "id": "user_124",
          "username": "alice",
          "avatarUrl": "https://api.dicebear.com/7.x/avataaars/svg?seed=Alice"
        }
      ],
      "createdAt": "2025-10-18T16:04:07.065Z"
    },
    {
      "id": "group_03f22c4d",
      "title": "afdadfa",
      "topic": "aadfadfa",
      "description": "",
      "host": {
        "id": "user_124",
        "username": "alice",
        "avatarUrl": "https://api.dicebear.com/7.x/avataaars/svg?seed=Alice"
      },
      "scheduledAt": "2025-10-18T16:42:00.706Z",
      "duration": 90,
      "maxParticipants": 8,
      "participants": [
        {
          "id": "user_124",
          "username": "alice",
          "avatarUrl": "https://api.dicebear.com/7.x/avataaars/svg?seed=Alice"
        }
      ],
      "createdAt": "2025-10-18T16:42:00.717Z"
    },
    {
      "id": "group_ba13caf3",
      "title": "afdadfa",
      "topic": "deeo learning",
      "description": "",
      "host": {
        "id": "user_124",
        "username": "alice",
        "avatarUrl": "https://api.dicebear.com/7.x/avataaars/svg?seed=Alice"
      },
      "scheduledAt": "2025-10-19T00:23:04.951Z",
      "duration": 90,
      "maxParticipants": 8,
      "participants": [
        {
          "id": "user_124",
          "username": "alice",
          "avatarUrl": "https://api.dicebear.com/7.x/avataaars/svg?seed=Alice"
        }
      ],
      "createdAt": "2025-10-19T00:23:04.982Z"
    },
    {
      "id": "group_b2011c34",
      "title": "DSA",
      "topic": "LL",
      "description": "",
      "host": {
        "id": "user_124",
        "username": "alice",
        "avatarUrl": "https://api.dicebear.com/7.x/avataaars/svg?seed=Alice"
      },
      "scheduledAt": "2025-10-19T05:11:34.356Z",
      "duration": 90,
      "maxParticipants": 8,
      "participants": [
        {
          "id": "user_124",
          "username": "alice",
          "avatarUrl": "https://api.dicebear.com/7.x/avataaars/svg?seed=Alice"
        }
      ],
      "createdAt": "2025-10-19T05:11:34.366Z"
    }
  ],
  "mySessions": []
}